{
  "pools": [
    {
      "bonus_rolls": 0.0,
      "conditions": [
        {
          "condition": "minecraft:inverted",
          "term": {
            "condition": "minecraft:match_tool",
            "predicate": {
              "enchantments": [
                {
                  "enchantment": "dadobugbedrockores:curse_of_fracturing",
                  "levels": {
                    "min": 1
                  }
                }
              ]
            }
          }
        },
        {
          "condition": "minecraft:inverted",
          "term": {
            "condition": "minecraft:match_tool",
            "predicate": {
              "enchantments": [
                {
                  "enchantment": "dadobugbedrockores:extraction",
                  "levels": {
                    "min": 1
                  }
                }
              ]
            }
          }
        },
        {
          "condition": "minecraft:inverted",
          "term": {
            "condition": "minecraft:match_tool",
            "predicate": {
              "enchantments": [
                {
                  "enchantment": "dadobugbedrockores:curse_of_shattering",
                  "levels": {
                    "min": 1
                  }
                }
              ]
            }
          }
        },
        {
          "condition": "minecraft:inverted",
          "term": {
            "condition": "minecraft:match_tool",
            "predicate": {
              "enchantments": [
                {
                  "enchantment": "dadobugbedrockores:arcane_extraction",
                  "levels": {
                    "min": 1
                  }
                }
              ]
            }
          }
        }
      ],
      "entries": [
        {
          "type": "minecraft:loot_table",
          "conditions": [
            {
              "condition": "dadobugbedrockores:modloaded",
              "mod_id": "mythicmetals"
            }
          ],
          "name": "mythicmetals:blocks/osmium_ore"
        }
      ],
      "name": "bedrock_mm_osmium_ore",
      "rolls": 1.0
    },
    {
      "bonus_rolls": 0.0,
      "conditions": [
        {
          "condition": "minecraft:match_tool",
          "predicate": {
            "enchantments": [
              {
                "enchantment": "dadobugbedrockores:extraction",
                "levels": {
                  "min": 1
                }
              }
            ]
          }
        }
      ],
      "entries": [
        {
          "type": "minecraft:item",
          "functions": [
            {
              "function": "minecraft:copy_nbt",
              "ops": [
                {
                  "op": "replace",
                  "source": "durability",
                  "target": "BlockEntityTag.durability"
                }
              ],
              "source": "block_entity"
            }
          ],
          "name": "dadobugbedrockores:regenerative_mm_osmium"
        }
      ],
      "name": "bedrock_mm_osmium_ore",
      "rolls": 1.0
    },
    {
      "bonus_rolls": 0.0,
      "conditions": [
        {
          "condition": "minecraft:match_tool",
          "predicate": {
            "enchantments": [
              {
                "enchantment": "dadobugbedrockores:arcane_extraction",
                "levels": {
                  "min": 1
                }
              }
            ]
          }
        }
      ],
      "entries": [
        {
          "type": "minecraft:item",
          "functions": [
            {
              "function": "minecraft:copy_nbt",
              "ops": [
                {
                  "op": "replace",
                  "source": "durability",
                  "target": "BlockEntityTag.durability"
                }
              ],
              "source": "block_entity"
            }
          ],
          "name": "dadobugbedrockores:bedrock_mm_osmium_ore"
        }
      ],
      "name": "bedrock_mm_osmium_ore",
      "rolls": 1.0
    }
  ]
}